MANIFEST.in
README.md
requirements.txt
setup.py
data_howdah/__init__.py
data_howdah/_obfuscate.py
data_howdah/data_howdah.py
data_howdah/secret.py
data_howdah/test.py
data_howdah.egg-info/PKG-INFO
data_howdah.egg-info/SOURCES.txt
data_howdah.egg-info/dependency_links.txt
data_howdah.egg-info/requires.txt
data_howdah.egg-info/top_level.txt