Metadata-Version: 2.1
Name: data-howdah
Version: 1.0.3
Summary: Effortlessly mask and encrypt your data frames for safe travel from computer to computer
Home-page: https://github.com/mustafah/data-howdah
Author: mustafah
Author-email: mustafah.elbanna@gmail.com
License: Apache 2.0
Keywords: data-protection,data-encryption,data-security,data-privacy,data-masking,dataframe-encryption,dataframe-security,pandas-dataframe,secure-data-transfer,data-anonymization,python-security,data-encryption-tool,data-safety,data-confidentiality,dataframe-protection
Requires-Python: >=3.7.1
Requires-Dist: pandas
Requires-Dist: matplotlib
Requires-Dist: ipython
Requires-Dist: numpy
Requires-Dist: cryptography
Requires-Dist: matplotlib
Requires-Dist: mplcyberpunk
Requires-Dist: tqdm
Requires-Dist: azure-keyvault-secrets
Requires-Dist: azure-identity
